tronclipy/__init__.py
tronclipy/main.py
tronclipy-0.0.1.dist-info/LICENSE.txt
tronclipy-0.0.1.dist-info/METADATA
tronclipy-0.0.1.dist-info/WHEEL
tronclipy-0.0.1.dist-info/top_level.txt
tronclipy-0.0.1.dist-info/RECORD
