Metadata-Version: 2.1
Name: tronclipy
Version: 0.0.1
Summary: tronclipy library for Python
Author: sventron
Author-email: hocixi6652@deenur.com
License: MIT
Project-URL: Source Repository, https://github.com
License-File: LICENSE.txt
Requires-Dist: requests
